securescanner/__init__.py
securescanner/cli.py
securescanner/scanner.py
securescanner/version.py
securescanner-0.1.0.dist-info/licenses/LICENSE
securescanner-0.1.0.dist-info/METADATA
securescanner-0.1.0.dist-info/WHEEL
securescanner-0.1.0.dist-info/entry_points.txt
securescanner-0.1.0.dist-info/top_level.txt
securescanner-0.1.0.dist-info/RECORD
